cloogle.py
cloogle-1.0.7.dist-info/DESCRIPTION.rst
cloogle-1.0.7.dist-info/METADATA
cloogle-1.0.7.dist-info/RECORD
cloogle-1.0.7.dist-info/WHEEL
cloogle-1.0.7.dist-info/metadata.json
cloogle-1.0.7.dist-info/top_level.txt
