Metadata-Version: 2.0
Name: cloogle
Version: 1.0.7
Summary: Basic interface to the Cloogle API
Home-page: https://gitlab.science.ru.nl/cloogle/cloogle-py
Author: Camil Staps
Author-email: info@camilstaps.nl
License: MIT
Keywords: cloogle api search clean
Platform: UNKNOWN
Classifier: Development Status :: 5 - Production/Stable
Classifier: Intended Audience :: Developers
Classifier: Intended Audience :: Information Technology
Classifier: Intended Audience :: Science/Research
Classifier: License :: OSI Approved :: MIT License
Classifier: Operating System :: OS Independent
Classifier: Programming Language :: Python
Classifier: Programming Language :: Python :: 3
Classifier: Programming Language :: Python :: 3 :: Only
Classifier: Topic :: Software Development :: Documentation
Classifier: Topic :: Utilities
